lastfmtwitter/__init__.py
lastfmtwitter/lastfm_twitter.py
lastfmtwitter/tests/__init__.py
lastfmtwitter/tests/test_lastfmtwitter.py
lastfmtwitter-0.7.3.dist-info/METADATA
lastfmtwitter-0.7.3.dist-info/WHEEL
lastfmtwitter-0.7.3.dist-info/top_level.txt
lastfmtwitter-0.7.3.dist-info/RECORD
