Metadata-Version: 2.1
Name: lastfmtwitter
Version: 0.7.3
Summary: Post your top weekly or yearly scrobbled artists to twitter.
Home-page: http://server.ericsbinaryworld.com/gpl_code/lastfmtwitter/index.html
Author: Eric Mesa
Author-email: eric@ericmesa.com
License: GPLv3
Keywords: twitter,lastfm
Platform: UNKNOWN
Classifier: Environment :: Console
Classifier: Intended Audience :: End Users/Desktop
Classifier: License :: OSI Approved :: GNU General Public License v3 (GPLv3)
Classifier: Programming Language :: Python :: 3
Requires-Dist: argparse
Requires-Dist: pylast
Requires-Dist: twitter
